p_1/__init__.py
p_1/first.py
p_1/second.py
p_1-1.0.1.dist-info/LICENSE
p_1-1.0.1.dist-info/METADATA
p_1-1.0.1.dist-info/WHEEL
p_1-1.0.1.dist-info/entry_points.txt
p_1-1.0.1.dist-info/top_level.txt
p_1-1.0.1.dist-info/RECORD
