Metadata-Version: 2.1
Name: p-1
Version: 1.0.1
Summary: A Python package to get my name
Home-page: https://github.com/nikhilkumarsingh/weather-reporter
Author: Mukul Agrawal
Author-email: agmukul63@gmail.com
License: MIT
Platform: UNKNOWN
Classifier: License :: OSI Approved :: MIT License
Classifier: Programming Language :: Python :: 3
Classifier: Programming Language :: Python :: 3.7
